odoo/addons/model_serializer/README.rst
odoo/addons/model_serializer/__init__.py
odoo/addons/model_serializer/__manifest__.py
odoo/addons/model_serializer/builder.py
odoo/addons/model_serializer/core.py
odoo/addons/model_serializer/field_converter.py
odoo/addons/model_serializer/serializers.py
odoo/addons/model_serializer/i18n/model_serializer.pot
odoo/addons/model_serializer/readme/CONTRIBUTORS.rst
odoo/addons/model_serializer/readme/DESCRIPTION.rst
odoo/addons/model_serializer/readme/HISTORY.rst
odoo/addons/model_serializer/readme/USAGE.rst
odoo/addons/model_serializer/static/description/icon.png
odoo/addons/model_serializer/static/description/index.html
odoo/addons/model_serializer/tests/__init__.py
odoo/addons/model_serializer/tests/test_model_serializer.py
odoo_addon_model_serializer-15.0.1.2.0.1.dist-info/METADATA
odoo_addon_model_serializer-15.0.1.2.0.1.dist-info/WHEEL
odoo_addon_model_serializer-15.0.1.2.0.1.dist-info/top_level.txt
odoo_addon_model_serializer-15.0.1.2.0.1.dist-info/RECORD
