Metadata-Version: 2.1
Name: odoo-addon-model-serializer
Version: 15.0.1.2.0.1
Summary: Automatically translate Odoo models into Datamodels for (de)serialization
Home-page: https://github.com/OCA/rest-framework
Author: Wakari, Odoo Community Association (OCA)
Author-email: support@odoo-community.org
License: LGPL-3
Platform: UNKNOWN
Classifier: Programming Language :: Python
Classifier: Framework :: Odoo
Classifier: Framework :: Odoo :: 15.0
Classifier: License :: OSI Approved :: GNU Lesser General Public License v3 (LGPLv3)
Classifier: Development Status :: 3 - Alpha
Requires-Python: >=3.8
Requires-Dist: marshmallow
Requires-Dist: odoo-addon-datamodel <15.1dev,>=15.0dev
Requires-Dist: odoo <15.1dev,>=15.0a
